queenbee/__init__.py
queenbee/exceptions.py
queenbee/queenbee.py
queenbeethreading-1.0.dist-info/licenses/LICENSE
queenbeethreading-1.0.dist-info/METADATA
queenbeethreading-1.0.dist-info/WHEEL
queenbeethreading-1.0.dist-info/top_level.txt
queenbeethreading-1.0.dist-info/RECORD
