Metadata-Version: 2.4
Name: queenbeethreading
Version: 1.0
Summary: A package that streamlines Python threading
Author-email: puzzle00 <email@example.com>
License-Expression: MIT
Project-URL: Homepage, https://github.com/puzzle00/queenbeethreading
Project-URL: Issues, https://github.com/puzzle00/queenbeethreading/issues
Classifier: Programming Language :: Python :: 3
Classifier: Operating System :: OS Independent
Requires-Python: >=3.9
License-File: LICENSE
Dynamic: license-file
